<OutputFiles>
 <File Object="unknown" Type="tci" Format="Text" Path="Job_02.tci" Hash="7be66890be6f28ce9822c62bc31dccc7" SubObject="unknown"/>
 <File Object="unknown" Type="tor" Format="Text" Path="Job_02.tor" Hash="1af188feed97d1708fbea5dc06ee4a7e" SubObject="unknown"/>
 <File Object="unknown" Type="out" Format="Text" Path="Job_02.out" Hash="d96ceb5e582be4d27f27361b77cc6196" SubObject="unknown"/>
 <File Object="bor_mom" Type="3D:CurrentsColourPlot" Format="Bin" Path="bor_mom.cpf" Hash="4bdfc1b4a87ec3777cefd0e010ac1e3d" SubObject="unknown">
  <Meta Values="bor_mom" Name="CurrentObject"/>
  <Parameter Values=" 30.0000000000000" Unit="GHz" Name="Frequency"/>
 </File>
 <File Object="lens_cut" Type="Cut:Spherical" Format="Ticra" Path="lens_cut.cut" Quantity="E" Hash="6013bab60eb856515d8f60f4cbd5baaa" SubObject="unknown">
  <Parameter Values=" 30.0000000000000" Unit="GHz" Name="Frequency"/>
  <Parameter Values="[0.000000000000000E+000;90.0000000000000;3]" Unit="deg" Name="Phi"/>
  <Parameter Values="[-180.000000000000;180.000000000000;601]" Unit="deg" Name="Theta"/>
  <Scan Type="polar"/>
 </File>
 <File Type="Comments" Format="Text" Path="comments.txt"/>
 <File Type="Screen" Format="Text" Path="screenoutput.txt"/>
</OutputFiles>
